siti_tools/__init__.py
siti_tools/__main__.py
siti_tools/file.py
siti_tools/log.py
siti_tools/siti.py
siti_tools-0.6.0.dist-info/WHEEL
siti_tools-0.6.0.dist-info/entry_points.txt
siti_tools-0.6.0.dist-info/METADATA
siti_tools-0.6.0.dist-info/RECORD
