Metadata-Version: 2.4
Name: siti-tools
Version: 0.6.0
Summary: Functions to calculate Spatial Information / Temporal Information according to ITU-T P.910
Keywords: video,spatial information,temporal information
Author: Werner Robitza, Lukas Krasula, Cosmin Stejerean
Author-email: Werner Robitza <werner.robitza@gmail.com>
License-Expression: MIT
Classifier: Development Status :: 4 - Beta
Classifier: Intended Audience :: Developers
Classifier: Topic :: Multimedia :: Video
Classifier: License :: OSI Approved :: MIT License
Classifier: Natural Language :: English
Classifier: Programming Language :: Python :: 3
Classifier: Programming Language :: Python :: 3.10
Classifier: Programming Language :: Python :: 3.11
Classifier: Programming Language :: Python :: 3.12
Classifier: Programming Language :: Python :: 3.13
Requires-Dist: scipy>=1.11.0
Requires-Dist: numpy>=2.0.0
Requires-Dist: av>=15.1.0
Requires-Dist: tqdm>=4.66.0
Requires-Dist: plotille>=5.0.0
Requires-Python: >=3.10.1
Project-URL: Homepage, https://github.com/VQEG/siti-tools
Project-URL: Repository, https://github.com/VQEG/siti-tools
